Metadata-Version: 2.1
Name: chpronounce
Version: 0.1.3
Summary: Convert Chinese to zhuyin(bopomofo) or pinyin
Home-page: https://github.com/YiPrograms/chpronounce
Author: Yi Kuo
Author-email: kuokuoyiyi@gmail.com
License: MIT
Keywords: chinese pinyin zhuyin bopomofo
Platform: UNKNOWN
Classifier: Development Status :: 3 - Alpha
Classifier: Intended Audience :: Developers
Classifier: Intended Audience :: Science/Research
Classifier: License :: OSI Approved :: MIT License
Classifier: Natural Language :: Chinese (Traditional)
Classifier: Natural Language :: Chinese (Traditional)
Classifier: Programming Language :: Python
Classifier: Programming Language :: Python :: 3.7
Classifier: Topic :: Text Processing :: Linguistic
Classifier: Topic :: Software Development :: Libraries :: Python Modules
Requires-Python: >=3
